{
	"info": {
		"_postman_id": "cb076831-0128-43ce-9f37-abf4557b5953",
		"name": "Kalaha",
		"schema": "https://schema.getpostman.com/json/collection/v2.1.0/collection.json",
		"_exporter_id": "14660437"
	},
	"item": [
		{
			"name": "createNewGame",
			"request": {
				"method": "POST",
				"header": [],
				"url": {
					"raw": "http://localhost:8080/kalahaGame",
					"protocol": "http",
					"host": [
						"localhost"
					],
					"port": "8080",
					"path": [
						"kalahaGame"
					]
				}
			},
			"response": []
		},
		{
			"name": "getGame",
			"request": {
				"method": "GET",
				"header": [],
				"url": {
					"raw": "http://localhost:8080/kalahaGame/1",
					"protocol": "http",
					"host": [
						"localhost"
					],
					"port": "8080",
					"path": [
						"kalahaGame",
						"1"
					]
				}
			},
			"response": []
		},
		{
			"name": "playGame",
			"request": {
				"method": "POST",
				"header": [],
				"body": {
					"mode": "raw",
					"raw": "{\r\n  \"gameId\": 1,\r\n  \"selectedPitId\": 1\r\n}",
					"options": {
						"raw": {
							"language": "json"
						}
					}
				},
				"url": {
					"raw": "http://localhost:8080/kahalaGame/playGame",
					"protocol": "http",
					"host": [
						"localhost"
					],
					"port": "8080",
					"path": [
						"kahalaGame",
						"playGame"
					]
				}
			},
			"response": []
		}
	]
}